{
  "history": [
    {
      "timestamp": "2026-04-19T16:50:03.677115",
      "error_rate": 3.12,
      "error_count": 393,
      "msg_count": 12595
    },
    {
      "timestamp": "2026-04-19T16:50:04.436193",
      "error_rate": 3.12,
      "error_count": 393,
      "msg_count": 12595
    },
    {
      "timestamp": "2026-04-19T16:50:05.079392",
      "error_rate": 3.12,
      "error_count": 393,
      "msg_count": 12595
    },
    {
      "timestamp": "2026-04-19T16:50:05.800687",
      "error_rate": 3.12,
      "error_count": 393,
      "msg_count": 12595
    },
    {
      "timestamp": "2026-04-19T16:50:34.841278",
      "error_rate": 3.12,
      "error_count": 393,
      "msg_count": 12611
    },
    {
      "timestamp": "2026-04-19T16:50:40.583695",
      "error_rate": 3.12,
      "error_count": 393,
      "msg_count": 12611
    },
    {
      "timestamp": "2026-04-19T16:50:41.259095",
      "error_rate": 3.12,
      "error_count": 393,
      "msg_count": 12611
    },
    {
      "timestamp": "2026-04-19T16:50:41.858444",
      "error_rate": 3.12,
      "error_count": 393,
      "msg_count": 12611
    },
    {
      "timestamp": "2026-04-19T16:50:42.489893",
      "error_rate": 3.12,
      "error_count": 393,
      "msg_count": 12611
    },
    {
      "timestamp": "2026-04-19T17:03:49.375725",
      "error_rate": 3.05,
      "error_count": 401,
      "msg_count": 13158
    },
    {
      "timestamp": "2026-04-19T17:03:50.930521",
      "error_rate": 3.05,
      "error_count": 401,
      "msg_count": 13158
    },
    {
      "timestamp": "2026-04-19T17:03:51.939557",
      "error_rate": 3.05,
      "error_count": 401,
      "msg_count": 13160
    },
    {
      "timestamp": "2026-04-19T17:03:52.630841",
      "error_rate": 3.05,
      "error_count": 401,
      "msg_count": 13160
    },
    {
      "timestamp": "2026-04-19T17:03:53.347010",
      "error_rate": 3.05,
      "error_count": 401,
      "msg_count": 13160
    },
    {
      "timestamp": "2026-04-19T18:08:40.630523",
      "error_rate": 3.05,
      "error_count": 366,
      "msg_count": 12000
    },
    {
      "timestamp": "2026-04-19T18:08:41.354142",
      "error_rate": 3.05,
      "error_count": 366,
      "msg_count": 12000
    },
    {
      "timestamp": "2026-04-19T18:08:42.041601",
      "error_rate": 3.05,
      "error_count": 366,
      "msg_count": 12000
    },
    {
      "timestamp": "2026-04-19T18:08:42.631158",
      "error_rate": 3.05,
      "error_count": 366,
      "msg_count": 12000
    },
    {
      "timestamp": "2026-04-19T18:08:43.379840",
      "error_rate": 3.05,
      "error_count": 366,
      "msg_count": 12000
    },
    {
      "timestamp": "2026-04-19T19:02:50.616106",
      "error_rate": 3.02,
      "error_count": 368,
      "msg_count": 12174
    },
    {
      "timestamp": "2026-04-19T19:02:51.356316",
      "error_rate": 3.02,
      "error_count": 368,
      "msg_count": 12174
    },
    {
      "timestamp": "2026-04-19T19:02:52.136652",
      "error_rate": 3.02,
      "error_count": 368,
      "msg_count": 12174
    },
    {
      "timestamp": "2026-04-19T19:02:52.782047",
      "error_rate": 3.02,
      "error_count": 368,
      "msg_count": 12174
    },
    {
      "timestamp": "2026-04-19T19:02:53.491204",
      "error_rate": 3.02,
      "error_count": 368,
      "msg_count": 12174
    },
    {
      "timestamp": "2026-04-19T20:05:57.248060",
      "error_rate": 3.08,
      "error_count": 376,
      "msg_count": 12224
    },
    {
      "timestamp": "2026-04-19T20:05:57.925864",
      "error_rate": 3.08,
      "error_count": 376,
      "msg_count": 12224
    },
    {
      "timestamp": "2026-04-19T20:05:58.597678",
      "error_rate": 3.08,
      "error_count": 376,
      "msg_count": 12224
    },
    {
      "timestamp": "2026-04-19T20:05:59.225984",
      "error_rate": 3.08,
      "error_count": 376,
      "msg_count": 12224
    },
    {
      "timestamp": "2026-04-19T20:05:59.813438",
      "error_rate": 3.08,
      "error_count": 376,
      "msg_count": 12224
    },
    {
      "timestamp": "2026-04-20T06:10:54.593557",
      "error_rate": 3.0,
      "error_count": 378,
      "msg_count": 12618
    },
    {
      "timestamp": "2026-04-20T06:10:55.345889",
      "error_rate": 3.0,
      "error_count": 378,
      "msg_count": 12618
    },
    {
      "timestamp": "2026-04-20T06:10:55.963435",
      "error_rate": 3.0,
      "error_count": 378,
      "msg_count": 12618
    },
    {
      "timestamp": "2026-04-20T06:10:56.559817",
      "error_rate": 3.0,
      "error_count": 378,
      "msg_count": 12618
    },
    {
      "timestamp": "2026-04-20T06:10:57.273941",
      "error_rate": 3.0,
      "error_count": 378,
      "msg_count": 12618
    },
    {
      "timestamp": "2026-04-20T06:20:05.588702",
      "error_rate": 3.06,
      "error_count": 312,
      "msg_count": 10194
    },
    {
      "timestamp": "2026-04-20T06:20:06.172473",
      "error_rate": 3.06,
      "error_count": 312,
      "msg_count": 10194
    },
    {
      "timestamp": "2026-04-20T06:20:06.741373",
      "error_rate": 3.06,
      "error_count": 312,
      "msg_count": 10194
    },
    {
      "timestamp": "2026-04-20T06:20:07.215260",
      "error_rate": 3.06,
      "error_count": 312,
      "msg_count": 10194
    },
    {
      "timestamp": "2026-04-20T06:20:07.771055",
      "error_rate": 3.06,
      "error_count": 312,
      "msg_count": 10194
    },
    {
      "timestamp": "2026-04-20T06:22:00.666122",
      "error_rate": 3.06,
      "error_count": 313,
      "msg_count": 10220
    },
    {
      "timestamp": "2026-04-20T06:22:01.278763",
      "error_rate": 3.06,
      "error_count": 313,
      "msg_count": 10220
    },
    {
      "timestamp": "2026-04-20T06:22:04.946916",
      "error_rate": 3.06,
      "error_count": 313,
      "msg_count": 10221
    },
    {
      "timestamp": "2026-04-20T06:22:05.593666",
      "error_rate": 3.06,
      "error_count": 313,
      "msg_count": 10221
    },
    {
      "timestamp": "2026-04-20T06:22:06.165274",
      "error_rate": 3.06,
      "error_count": 313,
      "msg_count": 10221
    },
    {
      "timestamp": "2026-04-20T06:22:06.678473",
      "error_rate": 3.06,
      "error_count": 313,
      "msg_count": 10221
    },
    {
      "timestamp": "2026-04-20T06:22:07.225790",
      "error_rate": 3.07,
      "error_count": 314,
      "msg_count": 10224
    },
    {
      "timestamp": "2026-04-20T06:22:10.134755",
      "error_rate": 3.07,
      "error_count": 314,
      "msg_count": 10225
    },
    {
      "timestamp": "2026-04-20T06:22:10.749770",
      "error_rate": 3.07,
      "error_count": 314,
      "msg_count": 10225
    },
    {
      "timestamp": "2026-04-20T06:22:11.305669",
      "error_rate": 3.07,
      "error_count": 314,
      "msg_count": 10226
    },
    {
      "timestamp": "2026-04-20T06:22:11.790131",
      "error_rate": 3.07,
      "error_count": 314,
      "msg_count": 10226
    },
    {
      "timestamp": "2026-04-20T06:22:12.380763",
      "error_rate": 3.07,
      "error_count": 314,
      "msg_count": 10226
    },
    {
      "timestamp": "2026-04-20T07:03:20.064026",
      "error_rate": 3.16,
      "error_count": 311,
      "msg_count": 9830
    },
    {
      "timestamp": "2026-04-20T07:03:20.665720",
      "error_rate": 3.16,
      "error_count": 311,
      "msg_count": 9830
    },
    {
      "timestamp": "2026-04-20T07:03:21.259385",
      "error_rate": 3.16,
      "error_count": 311,
      "msg_count": 9830
    },
    {
      "timestamp": "2026-04-20T07:03:21.759910",
      "error_rate": 3.16,
      "error_count": 311,
      "msg_count": 9830
    },
    {
      "timestamp": "2026-04-20T07:03:22.308028",
      "error_rate": 3.16,
      "error_count": 311,
      "msg_count": 9830
    },
    {
      "timestamp": "2026-04-20T07:34:03.313479",
      "error_rate": 3.04,
      "error_count": 316,
      "msg_count": 10379
    },
    {
      "timestamp": "2026-04-20T07:34:03.987540",
      "error_rate": 3.04,
      "error_count": 316,
      "msg_count": 10379
    },
    {
      "timestamp": "2026-04-20T07:34:04.667382",
      "error_rate": 3.04,
      "error_count": 316,
      "msg_count": 10379
    },
    {
      "timestamp": "2026-04-20T07:34:05.178622",
      "error_rate": 3.04,
      "error_count": 316,
      "msg_count": 10379
    },
    {
      "timestamp": "2026-04-20T07:34:05.790856",
      "error_rate": 3.04,
      "error_count": 316,
      "msg_count": 10379
    },
    {
      "timestamp": "2026-04-20T09:52:20.393594",
      "error_rate": 2.83,
      "error_count": 319,
      "msg_count": 11276
    },
    {
      "timestamp": "2026-04-20T16:17:13.314203",
      "error_rate": 2.52,
      "error_count": 279,
      "msg_count": 11065
    },
    {
      "timestamp": "2026-04-20T16:17:35.899918",
      "error_rate": 2.52,
      "error_count": 279,
      "msg_count": 11071
    },
    {
      "timestamp": "2026-04-20T16:37:45.415445",
      "error_rate": 2.48,
      "error_count": 274,
      "msg_count": 11057
    },
    {
      "timestamp": "2026-04-20T17:04:49.540461",
      "error_rate": 2.52,
      "error_count": 290,
      "msg_count": 11524
    },
    {
      "timestamp": "2026-04-20T18:01:52.670571",
      "error_rate": 2.48,
      "error_count": 284,
      "msg_count": 11473
    },
    {
      "timestamp": "2026-04-20T18:05:06.946354",
      "error_rate": 2.47,
      "error_count": 284,
      "msg_count": 11481
    },
    {
      "timestamp": "2026-04-20T18:05:07.662277",
      "error_rate": 2.47,
      "error_count": 284,
      "msg_count": 11481
    },
    {
      "timestamp": "2026-04-20T18:06:36.689358",
      "error_rate": 2.97,
      "error_count": 218,
      "msg_count": 7339
    },
    {
      "timestamp": "2026-04-20T19:04:28.086964",
      "error_rate": 2.85,
      "error_count": 199,
      "msg_count": 6990
    },
    {
      "timestamp": "2026-04-20T19:08:19.848813",
      "error_rate": 2.86,
      "error_count": 200,
      "msg_count": 6988
    },
    {
      "timestamp": "2026-04-20T19:10:03.662492",
      "error_rate": 2.85,
      "error_count": 200,
      "msg_count": 7007
    },
    {
      "timestamp": "2026-04-20T19:10:48.423118",
      "error_rate": 2.85,
      "error_count": 200,
      "msg_count": 7014
    },
    {
      "timestamp": "2026-04-20T19:10:48.850843",
      "error_rate": 2.85,
      "error_count": 200,
      "msg_count": 7014
    },
    {
      "timestamp": "2026-04-20T19:10:51.424645",
      "error_rate": 2.85,
      "error_count": 200,
      "msg_count": 7014
    },
    {
      "timestamp": "2026-04-20T19:12:00.097068",
      "error_rate": 2.86,
      "error_count": 200,
      "msg_count": 7002
    },
    {
      "timestamp": "2026-04-20T19:12:36.509811",
      "error_rate": 2.85,
      "error_count": 200,
      "msg_count": 7006
    },
    {
      "timestamp": "2026-04-20T19:12:36.907285",
      "error_rate": 2.85,
      "error_count": 200,
      "msg_count": 7006
    },
    {
      "timestamp": "2026-04-20T19:12:39.836279",
      "error_rate": 2.85,
      "error_count": 200,
      "msg_count": 7006
    },
    {
      "timestamp": "2026-04-20T19:13:54.268744",
      "error_rate": 2.85,
      "error_count": 200,
      "msg_count": 7008
    },
    {
      "timestamp": "2026-04-20T19:14:46.068842",
      "error_rate": 2.85,
      "error_count": 200,
      "msg_count": 7024
    },
    {
      "timestamp": "2026-04-20T19:14:46.454909",
      "error_rate": 2.85,
      "error_count": 200,
      "msg_count": 7024
    },
    {
      "timestamp": "2026-04-20T19:14:49.336989",
      "error_rate": 2.85,
      "error_count": 200,
      "msg_count": 7026
    },
    {
      "timestamp": "2026-04-20T19:15:57.544081",
      "error_rate": 2.84,
      "error_count": 200,
      "msg_count": 7047
    },
    {
      "timestamp": "2026-04-20T19:16:05.944404",
      "error_rate": 2.84,
      "error_count": 200,
      "msg_count": 7050
    },
    {
      "timestamp": "2026-04-20T19:16:06.423109",
      "error_rate": 2.84,
      "error_count": 200,
      "msg_count": 7050
    },
    {
      "timestamp": "2026-04-20T19:16:14.723094",
      "error_rate": 2.84,
      "error_count": 200,
      "msg_count": 7050
    },
    {
      "timestamp": "2026-04-20T19:17:31.553376",
      "error_rate": 2.78,
      "error_count": 194,
      "msg_count": 6990
    },
    {
      "timestamp": "2026-04-20T19:18:04.860820",
      "error_rate": 2.77,
      "error_count": 194,
      "msg_count": 6997
    },
    {
      "timestamp": "2026-04-20T19:18:05.274763",
      "error_rate": 2.77,
      "error_count": 194,
      "msg_count": 6997
    },
    {
      "timestamp": "2026-04-20T19:18:08.244007",
      "error_rate": 2.77,
      "error_count": 194,
      "msg_count": 6997
    },
    {
      "timestamp": "2026-04-20T19:19:25.729424",
      "error_rate": 2.77,
      "error_count": 194,
      "msg_count": 7001
    },
    {
      "timestamp": "2026-04-20T20:04:55.205944",
      "error_rate": 2.81,
      "error_count": 197,
      "msg_count": 7023
    },
    {
      "timestamp": "2026-04-20T20:45:26.652899",
      "error_rate": 2.71,
      "error_count": 193,
      "msg_count": 7110
    },
    {
      "timestamp": "2026-04-20T20:45:27.063195",
      "error_rate": 2.71,
      "error_count": 193,
      "msg_count": 7110
    },
    {
      "timestamp": "2026-04-20T20:45:30.005336",
      "error_rate": 2.71,
      "error_count": 193,
      "msg_count": 7110
    },
    {
      "timestamp": "2026-04-20T20:46:48.884025",
      "error_rate": 2.71,
      "error_count": 193,
      "msg_count": 7112
    },
    {
      "timestamp": "2026-04-20T21:04:31.425360",
      "error_rate": 2.74,
      "error_count": 197,
      "msg_count": 7195
    },
    {
      "timestamp": "2026-04-20T22:02:43.115244",
      "error_rate": 2.71,
      "error_count": 199,
      "msg_count": 7335
    }
  ]
}