{
  "runs": [
    {
      "timestamp": "2026-04-11T10:09:56.623186",
      "phase": "system_check",
      "success": true,
      "notes": "[]"
    },
    {
      "timestamp": "2026-04-11T10:10:00.040400",
      "phase": "research",
      "success": true,
      "notes": ""
    },
    {
      "timestamp": "2026-04-11T10:10:00.209350",
      "phase": "quality",
      "success": false,
      "notes": ""
    },
    {
      "timestamp": "2026-04-11T10:10:00.395924",
      "phase": "learning",
      "success": true,
      "notes": ""
    },
    {
      "timestamp": "2026-04-11T10:42:01.974121",
      "phase": "system_check",
      "success": true,
      "notes": "[]"
    },
    {
      "timestamp": "2026-04-11T10:42:05.034064",
      "phase": "research",
      "success": true,
      "notes": ""
    },
    {
      "timestamp": "2026-04-11T10:42:05.192234",
      "phase": "quality",
      "success": false,
      "notes": ""
    },
    {
      "timestamp": "2026-04-11T10:42:05.323066",
      "phase": "learning",
      "success": true,
      "notes": ""
    },
    {
      "timestamp": "2026-04-11T10:42:35.421024",
      "phase": "system_check",
      "success": false,
      "notes": "['Gateway Check failed']"
    },
    {
      "timestamp": "2026-04-11T10:42:38.430357",
      "phase": "research",
      "success": true,
      "notes": ""
    },
    {
      "timestamp": "2026-04-11T10:42:38.621517",
      "phase": "quality",
      "success": true,
      "notes": ""
    },
    {
      "timestamp": "2026-04-11T10:42:38.780912",
      "phase": "learning",
      "success": true,
      "notes": ""
    },
    {
      "timestamp": "2026-04-11T10:43:09.285476",
      "phase": "system_check",
      "success": true,
      "notes": "[]"
    },
    {
      "timestamp": "2026-04-11T10:43:12.206241",
      "phase": "research",
      "success": true,
      "notes": ""
    },
    {
      "timestamp": "2026-04-11T10:43:12.364454",
      "phase": "quality",
      "success": true,
      "notes": ""
    },
    {
      "timestamp": "2026-04-11T10:43:12.503507",
      "phase": "learning",
      "success": true,
      "notes": ""
    },
    {
      "timestamp": "2026-04-11T11:04:58.967692",
      "phase": "system_check",
      "success": true,
      "notes": "[]"
    },
    {
      "timestamp": "2026-04-11T11:05:02.114583",
      "phase": "research",
      "success": true,
      "notes": ""
    },
    {
      "timestamp": "2026-04-11T11:05:02.332856",
      "phase": "quality",
      "success": true,
      "notes": ""
    },
    {
      "timestamp": "2026-04-11T11:05:02.510204",
      "phase": "learning",
      "success": true,
      "notes": ""
    }
  ],
  "last_full_cycle": "2026-04-11T11:05:02.510218"
}